fds/__init__.py
fds/sdk/__init__.py
fds/sdk/Classifications/__init__.py
fds/sdk/Classifications/api_client.py
fds/sdk/Classifications/configuration.py
fds/sdk/Classifications/exceptions.py
fds/sdk/Classifications/model_utils.py
fds/sdk/Classifications/rest.py
fds/sdk/Classifications/api/__init__.py
fds/sdk/Classifications/api/gics_api.py
fds/sdk/Classifications/apis/__init__.py
fds/sdk/Classifications/model/__init__.py
fds/sdk/Classifications/model/calendar.py
fds/sdk/Classifications/model/error_response.py
fds/sdk/Classifications/model/error_response_sub_errors.py
fds/sdk/Classifications/model/frequency.py
fds/sdk/Classifications/model/gics.py
fds/sdk/Classifications/model/gics_request.py
fds/sdk/Classifications/model/gics_response.py
fds/sdk/Classifications/model/ids.py
fds/sdk/Classifications/models/__init__.py
fds_sdk_classifications-1.0.15.dist-info/licenses/LICENSE
fds_sdk_classifications-1.0.15.dist-info/METADATA
fds_sdk_classifications-1.0.15.dist-info/WHEEL
fds_sdk_classifications-1.0.15.dist-info/top_level.txt
fds_sdk_classifications-1.0.15.dist-info/RECORD
