Metadata-Version: 2.4
Name: fds.sdk.Classifications
Version: 1.0.15
Summary: Classifications client library for Python
Home-page: https://github.com/FactSet/enterprise-sdk/tree/main/code/python/Classifications/v1
Author: FactSet Research Systems
License: Apache License, Version 2.0
Keywords: FactSet,API,SDK
Requires-Python: >=3.7
License-File: LICENSE
Requires-Dist: urllib3>=1.25.3
Requires-Dist: python-dateutil
Requires-Dist: fds.sdk.utils>=1.0.0
Dynamic: author
Dynamic: description
Dynamic: description-content-type
Dynamic: home-page
Dynamic: keywords
Dynamic: license
Dynamic: license-file
Dynamic: requires-dist
Dynamic: requires-python
Dynamic: summary
